langchain_qaip/__init__.py
langchain_qaip/retriever.py
langchain_qaip-0.1.5.dist-info/WHEEL
langchain_qaip-0.1.5.dist-info/METADATA
langchain_qaip-0.1.5.dist-info/RECORD
