Metadata-Version: 2.3
Name: langchain-qaip
Version: 0.1.5
Summary: An integration package connecting QAIP and LangChain
License: MIT
Requires-Dist: langchain-core>=0.3.45
Requires-Python: >=3.11.0
Project-URL: repository, https://github.com/qlonolink/langchain-qaip
